<?xml version="1.0" encoding="UTF-8" standalone="no"?>
<daw1>
    <alumno>
        <nombre>Víctor</nombre>
        <intervenciones>0</intervenciones>
        <fecha_intervencion>2023-01-01 00:00:00</fecha_intervencion>
    </alumno>
    <alumno>
        <nombre>Diego</nombre>
        <intervenciones>0</intervenciones>
        <fecha_intervencion>2023-01-01 00:00:00</fecha_intervencion>
    </alumno>
    <alumno>
        <nombre>Juan María</nombre>
        <intervenciones>0</intervenciones>
        <fecha_intervencion>2023-01-01 00:00:00</fecha_intervencion>
    </alumno>
    <alumno>
        <nombre>Pablo</nombre>
        <intervenciones>0</intervenciones>
        <fecha_intervencion>2023-01-01 00:00:00</fecha_intervencion>
    </alumno>
    <alumno>
        <nombre>Jorge</nombre>
        <intervenciones>0</intervenciones>
        <fecha_intervencion>2023-01-01 00:00:00</fecha_intervencion>
    </alumno>
    <alumno>
        <nombre>Adrián</nombre>
        <intervenciones>0</intervenciones>
        <fecha_intervencion>2023-01-01 00:00:00</fecha_intervencion>
    </alumno>
    <alumno>
        <nombre>Daniel</nombre>
        <intervenciones>0</intervenciones>
        <fecha_intervencion>2023-01-01 00:00:00</fecha_intervencion>
    </alumno>
    <alumno>
        <nombre>Jonathan</nombre>
        <intervenciones>0</intervenciones>
        <fecha_intervencion>2023-01-01 00:00:00</fecha_intervencion>
    </alumno>
    <alumno>
        <nombre>Juan Manuel Herrera</nombre>
        <intervenciones>0</intervenciones>
        <fecha_intervencion>2023-01-01 00:00:00</fecha_intervencion>
    </alumno>
    <alumno>
        <nombre>Juan Manuel Saborido</nombre>
        <intervenciones>0</intervenciones>
        <fecha_intervencion>2023-01-01 00:00:00</fecha_intervencion>
    </alumno>
    <alumno>
        <nombre>David</nombre>
        <intervenciones>0</intervenciones>
        <fecha_intervencion>2023-01-01 00:00:00</fecha_intervencion>
    </alumno>
    <alumno>
        <nombre>Antonio</nombre>
        <intervenciones>0</intervenciones>
        <fecha_intervencion>2023-01-01 00:00:00</fecha_intervencion>
    </alumno>
    <alumno>
        <nombre>Julián</nombre>
        <intervenciones>0</intervenciones>
        <fecha_intervencion>2023-01-01 00:00:00</fecha_intervencion>
    </alumno>
    <alumno>
        <nombre>Ricardo</nombre>
        <intervenciones>0</intervenciones>
        <fecha_intervencion>2023-01-01 00:00:00</fecha_intervencion>
    </alumno>
    <alumno>
        <nombre>Pepe</nombre>
        <intervenciones>0</intervenciones>
        <fecha_intervencion>2023-01-01 00:00:00</fecha_intervencion>
    </alumno>
</daw1>